digitex_bot_framework/__init__.py
digitex_bot_framework/bot.py
digitex_bot_framework/currency_pair.py
digitex_bot_framework/enums.py
digitex_bot_framework/market.py
digitex_bot_framework/order.py
digitex_bot_framework/order_book.py
digitex_bot_framework/position.py
digitex_bot_framework/tick.py
digitex_bot_framework/trade.py
digitex_bot_framework/trader.py
digitex_bot_framework/util.py
digitex_bot_framework-1.0.3.dist-info/LICENSE
digitex_bot_framework-1.0.3.dist-info/WHEEL
digitex_bot_framework-1.0.3.dist-info/METADATA
digitex_bot_framework-1.0.3.dist-info/RECORD
